RoboPy.py
RoboteqCPPimporter.py
RoboteqCommand.py
RoboteqSerialCommand.py
RoboteQPy-0.0.1.dist-info/METADATA
RoboteQPy-0.0.1.dist-info/WHEEL
RoboteQPy-0.0.1.dist-info/namespace_packages.txt
RoboteQPy-0.0.1.dist-info/top_level.txt
RoboteQPy-0.0.1.dist-info/zip-safe
RoboteQPy-0.0.1.dist-info/RECORD
