Metadata-Version: 2.1
Name: RoboteQPy
Version: 0.0.1
Summary: Module for interfacing Python with RoboteQ Products
Home-page: https://www.roboteq.com
Author: Gabriel Isko
Author-email: gabe.isko@gmail.com
License: MIT
Platform: UNKNOWN
Classifier: Development Status :: 3 - Alpha
Classifier: Programming Language :: Python
